honest_chain/__init__.py
honest_chain/bitcoin.meta.json
honest_chain/bitcoin.py
honest_chain/bitcoin.summary.md
honest_chain/core.meta.json
honest_chain/core.py
honest_chain/core.summary.md
honest_chain/identity.meta.json
honest_chain/identity.py
honest_chain/identity.summary.md
honest_chain/index.json
honest_chain/index.md
honest_chain/index.meta.json
honest_chain/index.summary.md
honest_chain/p2p.meta.json
honest_chain/p2p.py
honest_chain/p2p.summary.md
honest_chain-2.13.8.dist-info/METADATA
honest_chain-2.13.8.dist-info/WHEEL
honest_chain-2.13.8.dist-info/licenses/LICENSE
honest_chain-2.13.8.dist-info/RECORD
