Metadata-Version: 2.4
Name: honest-chain
Version: 2.13.8
Summary: Quantum-Ready AI Decision Audit Trail - Tamper-evident logging for AI systems
Project-URL: Homepage, https://github.com/Stellanium/honest-chain
Project-URL: Documentation, https://github.com/Stellanium/honest-chain#readme
Project-URL: Repository, https://github.com/Stellanium/honest-chain.git
Project-URL: Issues, https://github.com/Stellanium/honest-chain/issues
Project-URL: Changelog, https://github.com/Stellanium/honest-chain/releases
Author-email: Stellanium Ltd <admin@stellanium.io>
Maintainer-email: Stellanium Ltd <admin@stellanium.io>
License: MIT
License-File: LICENSE
Keywords: ai,audit,blockchain,cryptography,decision-logging,ethics,honesty,quantum-safe,sha3,transparency,trust
Classifier: Development Status :: 4 - Beta
Classifier: Intended Audience :: Developers
Classifier: Intended Audience :: Science/Research
Classifier: License :: OSI Approved :: MIT License
Classifier: Operating System :: OS Independent
Classifier: Programming Language :: Python :: 3
Classifier: Programming Language :: Python :: 3.8
Classifier: Programming Language :: Python :: 3.9
Classifier: Programming Language :: Python :: 3.10
Classifier: Programming Language :: Python :: 3.11
Classifier: Programming Language :: Python :: 3.12
Classifier: Topic :: Scientific/Engineering :: Artificial Intelligence
Classifier: Topic :: Security :: Cryptography
Classifier: Topic :: Software Development :: Libraries :: Python Modules
Classifier: Typing :: Typed
Requires-Python: >=3.8
Provides-Extra: bitcoin
Requires-Dist: bitcoinlib>=0.6.0; extra == 'bitcoin'
Provides-Extra: dev
Requires-Dist: black>=23.0; extra == 'dev'
Requires-Dist: cryptography>=41.0.0; extra == 'dev'
Requires-Dist: mypy>=1.0; extra == 'dev'
Requires-Dist: pytest-cov>=4.0; extra == 'dev'
Requires-Dist: pytest>=7.0; extra == 'dev'
Provides-Extra: ed25519
Requires-Dist: cryptography>=41.0.0; extra == 'ed25519'
Provides-Extra: full
Requires-Dist: bitcoinlib>=0.6.0; extra == 'full'
Requires-Dist: cryptography>=41.0.0; extra == 'full'
